LICENSE
MANIFEST.in
README.md
requirements.txt
setup.py
pyglance/__init__.py
pyglance.egg-info/PKG-INFO
pyglance.egg-info/SOURCES.txt
pyglance.egg-info/dependency_links.txt
pyglance.egg-info/entry_points.txt
pyglance.egg-info/requires.txt
pyglance.egg-info/top_level.txt